[
    {
        "forecast": [
            {
                "description": "broken clouds", 
                "rain": 0, 
                "wind_dir": 205.012, 
                "wind_speed": 1.28, 
                "clouds": 64, 
                "temp": 68.14, 
                "humidity": 28, 
                "pressure_sea": 1013.06, 
                "time": 1553644800, 
                "pressure_ground": 947.95, 
                "time_str": "2019-03-27 00:00:00"
            }, 
            {
                "description": "scattered clouds", 
                "rain": 0, 
                "wind_dir": 202.002, 
                "wind_speed": 0.92, 
                "clouds": 36, 
                "temp": 55.89, 
                "humidity": 48, 
                "pressure_sea": 1013.71, 
                "time": 1553655600, 
                "pressure_ground": 948.04, 
                "time_str": "2019-03-27 03:00:00"
            }, 
            {
                "description": "few clouds", 
                "rain": 0, 
                "wind_dir": 271.502, 
                "wind_speed": 0.53, 
                "clouds": 24, 
                "temp": 45.03, 
                "humidity": 80, 
                "pressure_sea": 1014.95, 
                "time": 1553666400, 
                "pressure_ground": 948.76, 
                "time_str": "2019-03-27 06:00:00"
            }, 
            {
                "description": "few clouds", 
                "rain": 0, 
                "wind_dir": 185.5, 
                "wind_speed": 0.66, 
                "clouds": 24, 
                "temp": 41.83, 
                "humidity": 83, 
                "pressure_sea": 1015.17, 
                "time": 1553677200, 
                "pressure_ground": 948.9, 
                "time_str": "2019-03-27 09:00:00"
            }, 
            {
                "description": "scattered clouds", 
                "rain": 0, 
                "wind_dir": 120.5, 
                "wind_speed": 0.56, 
                "clouds": 48, 
                "temp": 40.9, 
                "humidity": 84, 
                "pressure_sea": 1015.09, 
                "time": 1553688000, 
                "pressure_ground": 948.51, 
                "time_str": "2019-03-27 12:00:00"
            }, 
            {
                "description": "broken clouds", 
                "rain": 0, 
                "wind_dir": 133.002, 
                "wind_speed": 0.76, 
                "clouds": 64, 
                "temp": 44.38, 
                "humidity": 76, 
                "pressure_sea": 1016.59, 
                "time": 1553698800, 
                "pressure_ground": 949.81, 
                "time_str": "2019-03-27 15:00:00"
            }, 
            {
                "description": "scattered clouds", 
                "rain": 0, 
                "wind_dir": 194.008, 
                "wind_speed": 1.31, 
                "clouds": 32, 
                "temp": 59.89, 
                "humidity": 52, 
                "pressure_sea": 1017.3, 
                "time": 1553709600, 
                "pressure_ground": 951.08, 
                "time_str": "2019-03-27 18:00:00"
            }, 
            {
                "description": "clear sky", 
                "rain": 0, 
                "wind_dir": 215.002, 
                "wind_speed": 1.51, 
                "clouds": 0, 
                "temp": 66.43, 
                "humidity": 40, 
                "pressure_sea": 1015.69, 
                "time": 1553720400, 
                "pressure_ground": 950.2, 
                "time_str": "2019-03-27 21:00:00"
            }
        ], 
        "zip_code": "90042"
    }, 
    {
        "forecast": [
            {
                "description": "clear sky", 
                "rain": 0, 
                "wind_dir": 341.012, 
                "wind_speed": 4.78, 
                "clouds": 0, 
                "temp": 67.91, 
                "humidity": 57, 
                "pressure_sea": 1020.94, 
                "time": 1553644800, 
                "pressure_ground": 1020.83, 
                "time_str": "2019-03-27 00:00:00"
            }, 
            {
                "description": "clear sky", 
                "rain": 0, 
                "wind_dir": 359.502, 
                "wind_speed": 6.02, 
                "clouds": 0, 
                "temp": 63.61, 
                "humidity": 60, 
                "pressure_sea": 1023.27, 
                "time": 1553655600, 
                "pressure_ground": 1023.16, 
                "time_str": "2019-03-27 03:00:00"
            }, 
            {
                "description": "clear sky", 
                "rain": 0, 
                "wind_dir": 3.50201, 
                "wind_speed": 5.48, 
                "clouds": 0, 
                "temp": 59.81, 
                "humidity": 64, 
                "pressure_sea": 1023.83, 
                "time": 1553666400, 
                "pressure_ground": 1023.64, 
                "time_str": "2019-03-27 06:00:00"
            }, 
            {
                "description": "clear sky", 
                "rain": 0, 
                "wind_dir": 9.50024, 
                "wind_speed": 5.31, 
                "clouds": 0, 
                "temp": 57.18, 
                "humidity": 68, 
                "pressure_sea": 1023.89, 
                "time": 1553677200, 
                "pressure_ground": 1023.78, 
                "time_str": "2019-03-27 09:00:00"
            }, 
            {
                "description": "clear sky", 
                "rain": 0, 
                "wind_dir": 24.5001, 
                "wind_speed": 5.16, 
                "clouds": 0, 
                "temp": 54.85, 
                "humidity": 70, 
                "pressure_sea": 1025.65, 
                "time": 1553688000, 
                "pressure_ground": 1025.47, 
                "time_str": "2019-03-27 12:00:00"
            }, 
            {
                "description": "clear sky", 
                "rain": 0, 
                "wind_dir": 41.0021, 
                "wind_speed": 4.66, 
                "clouds": 0, 
                "temp": 57.52, 
                "humidity": 71, 
                "pressure_sea": 1026.55, 
                "time": 1553698800, 
                "pressure_ground": 1026.45, 
                "time_str": "2019-03-27 15:00:00"
            }, 
            {
                "description": "clear sky", 
                "rain": 0, 
                "wind_dir": 73.0081, 
                "wind_speed": 2.21, 
                "clouds": 0, 
                "temp": 62.86, 
                "humidity": 66, 
                "pressure_sea": 1026.54, 
                "time": 1553709600, 
                "pressure_ground": 1026.51, 
                "time_str": "2019-03-27 18:00:00"
            }, 
            {
                "description": "clear sky", 
                "rain": 0, 
                "wind_dir": 117.002, 
                "wind_speed": 3.21, 
                "clouds": 0, 
                "temp": 64.45, 
                "humidity": 61, 
                "pressure_sea": 1024.85, 
                "time": 1553720400, 
                "pressure_ground": 1024.84, 
                "time_str": "2019-03-27 21:00:00"
            }
        ], 
        "zip_code": "70119"
    }, 
    {
        "forecast": [
            {
                "description": "clear sky", 
                "rain": 0, 
                "wind_dir": 0.0120239, 
                "wind_speed": 3.48, 
                "clouds": 0, 
                "temp": 41.2, 
                "humidity": 67, 
                "pressure_sea": 1026.9, 
                "time": 1553644800, 
                "pressure_ground": 1023.39, 
                "time_str": "2019-03-27 00:00:00"
            }, 
            {
                "description": "clear sky", 
                "rain": 0, 
                "wind_dir": 6.00177, 
                "wind_speed": 3.72, 
                "clouds": 0, 
                "temp": 36.66, 
                "humidity": 73, 
                "pressure_sea": 1029.03, 
                "time": 1553655600, 
                "pressure_ground": 1025.4, 
                "time_str": "2019-03-27 03:00:00"
            }, 
            {
                "description": "clear sky", 
                "rain": 0, 
                "wind_dir": 3.00201, 
                "wind_speed": 3.98, 
                "clouds": 0, 
                "temp": 33.82, 
                "humidity": 76, 
                "pressure_sea": 1030.27, 
                "time": 1553666400, 
                "pressure_ground": 1026.68, 
                "time_str": "2019-03-27 06:00:00"
            }, 
            {
                "description": "clear sky", 
                "rain": 0, 
                "wind_dir": 14.5002, 
                "wind_speed": 3.71, 
                "clouds": 0, 
                "temp": 30.69, 
                "humidity": 80, 
                "pressure_sea": 1031.73, 
                "time": 1553677200, 
                "pressure_ground": 1028.1, 
                "time_str": "2019-03-27 09:00:00"
            }, 
            {
                "description": "clear sky", 
                "rain": 0, 
                "wind_dir": 37.0001, 
                "wind_speed": 3.16, 
                "clouds": 0, 
                "temp": 30.19, 
                "humidity": 81, 
                "pressure_sea": 1033.93, 
                "time": 1553688000, 
                "pressure_ground": 1030.35, 
                "time_str": "2019-03-27 12:00:00"
            }, 
            {
                "description": "clear sky", 
                "rain": 0, 
                "wind_dir": 55.5021, 
                "wind_speed": 2.51, 
                "clouds": 0, 
                "temp": 36.64, 
                "humidity": 74, 
                "pressure_sea": 1034.91, 
                "time": 1553698800, 
                "pressure_ground": 1031.33, 
                "time_str": "2019-03-27 15:00:00"
            }, 
            {
                "description": "clear sky", 
                "rain": 0, 
                "wind_dir": 84.0081, 
                "wind_speed": 1.71, 
                "clouds": 0, 
                "temp": 40.54, 
                "humidity": 73, 
                "pressure_sea": 1034.02, 
                "time": 1553709600, 
                "pressure_ground": 1030.51, 
                "time_str": "2019-03-27 18:00:00"
            }, 
            {
                "description": "clear sky", 
                "rain": 0, 
                "wind_dir": 140.002, 
                "wind_speed": 1.61, 
                "clouds": 8, 
                "temp": 41.59, 
                "humidity": 66, 
                "pressure_sea": 1032.73, 
                "time": 1553720400, 
                "pressure_ground": 1029.16, 
                "time_str": "2019-03-27 21:00:00"
            }
        ], 
        "zip_code": "11217"
    }
]