[
    {
        "forecast": [
            {
                "description": "few clouds", 
                "rain": 0, 
                "wind_dir": 228.008, 
                "wind_speed": 4.23, 
                "clouds": 20, 
                "temp": 86.36, 
                "humidity": 57, 
                "pressure_sea": 1012.4, 
                "time": 1566777600, 
                "pressure_ground": 1000.16, 
                "time_str": "2019-08-26 00:00:00"
            }, 
            {
                "description": "overcast clouds", 
                "rain": 0, 
                "wind_dir": 194.792, 
                "wind_speed": 2.57, 
                "clouds": 100, 
                "temp": 80.94, 
                "humidity": 63, 
                "pressure_sea": 1013.21, 
                "time": 1566788400, 
                "pressure_ground": 1000.35, 
                "time_str": "2019-08-26 03:00:00"
            }, 
            {
                "description": "overcast clouds", 
                "rain": 0, 
                "wind_dir": 199.595, 
                "wind_speed": 1.56, 
                "clouds": 100, 
                "temp": 76.84, 
                "humidity": 63, 
                "pressure_sea": 1013.29, 
                "time": 1566799200, 
                "pressure_ground": 1000.63, 
                "time_str": "2019-08-26 06:00:00"
            }, 
            {
                "description": "overcast clouds", 
                "rain": 0, 
                "wind_dir": 178.5, 
                "wind_speed": 0.96, 
                "clouds": 100, 
                "temp": 74.44, 
                "humidity": 62, 
                "pressure_sea": 1012.7, 
                "time": 1566810000, 
                "pressure_ground": 999.77, 
                "time_str": "2019-08-26 09:00:00"
            }, 
            {
                "description": "overcast clouds", 
                "rain": 0, 
                "wind_dir": 178.883, 
                "wind_speed": 0.72, 
                "clouds": 100, 
                "temp": 71.87, 
                "humidity": 62, 
                "pressure_sea": 1011.67, 
                "time": 1566820800, 
                "pressure_ground": 998.54, 
                "time_str": "2019-08-26 12:00:00"
            }, 
            {
                "description": "overcast clouds", 
                "rain": 0, 
                "wind_dir": 195.427, 
                "wind_speed": 1.17, 
                "clouds": 100, 
                "temp": 72.79, 
                "humidity": 60, 
                "pressure_sea": 1012.1, 
                "time": 1566831600, 
                "pressure_ground": 999.22, 
                "time_str": "2019-08-26 15:00:00"
            }, 
            {
                "description": "broken clouds", 
                "rain": 0, 
                "wind_dir": 166.744, 
                "wind_speed": 2.49, 
                "clouds": 78, 
                "temp": 78.53, 
                "humidity": 45, 
                "pressure_sea": 1012.04, 
                "time": 1566842400, 
                "pressure_ground": 999.6, 
                "time_str": "2019-08-26 18:00:00"
            }, 
            {
                "description": "scattered clouds", 
                "rain": 0, 
                "wind_dir": 201.067, 
                "wind_speed": 3.24, 
                "clouds": 29, 
                "temp": 78.39, 
                "humidity": 46, 
                "pressure_sea": 1010.08, 
                "time": 1566853200, 
                "pressure_ground": 998.02, 
                "time_str": "2019-08-26 21:00:00"
            }
        ], 
        "zip_code": "90042"
    }, 
    {
        "forecast": [
            {
                "description": "light rain", 
                "rain": 1.687, 
                "wind_dir": 208.834, 
                "wind_speed": 2.02, 
                "clouds": 100, 
                "temp": 78.31, 
                "humidity": 92, 
                "pressure_sea": 1012.07, 
                "time": 1566777600, 
                "pressure_ground": 1011.37, 
                "time_str": "2019-08-26 00:00:00"
            }, 
            {
                "description": "light rain", 
                "rain": 0.75, 
                "wind_dir": 212.847, 
                "wind_speed": 1.41, 
                "clouds": 100, 
                "temp": 77.07, 
                "humidity": 93, 
                "pressure_sea": 1012.65, 
                "time": 1566788400, 
                "pressure_ground": 1011.87, 
                "time_str": "2019-08-26 03:00:00"
            }, 
            {
                "description": "light rain", 
                "rain": 0.375, 
                "wind_dir": 187.373, 
                "wind_speed": 1.43, 
                "clouds": 100, 
                "temp": 75.52, 
                "humidity": 94, 
                "pressure_sea": 1011.84, 
                "time": 1566799200, 
                "pressure_ground": 1010.99, 
                "time_str": "2019-08-26 06:00:00"
            }, 
            {
                "description": "moderate rain", 
                "rain": 4.688, 
                "wind_dir": 156.496, 
                "wind_speed": 1.97, 
                "clouds": 100, 
                "temp": 74.41, 
                "humidity": 97, 
                "pressure_sea": 1010.92, 
                "time": 1566810000, 
                "pressure_ground": 1010.02, 
                "time_str": "2019-08-26 09:00:00"
            }, 
            {
                "description": "moderate rain", 
                "rain": 6.624, 
                "wind_dir": 173.519, 
                "wind_speed": 2.61, 
                "clouds": 100, 
                "temp": 74.03, 
                "humidity": 96, 
                "pressure_sea": 1011.38, 
                "time": 1566820800, 
                "pressure_ground": 1010.45, 
                "time_str": "2019-08-26 12:00:00"
            }, 
            {
                "description": "moderate rain", 
                "rain": 4, 
                "wind_dir": 184.199, 
                "wind_speed": 3.84, 
                "clouds": 100, 
                "temp": 80.89, 
                "humidity": 84, 
                "pressure_sea": 1012.21, 
                "time": 1566831600, 
                "pressure_ground": 1011.3, 
                "time_str": "2019-08-26 15:00:00"
            }, 
            {
                "description": "light rain", 
                "rain": 2.812, 
                "wind_dir": 207.182, 
                "wind_speed": 4.07, 
                "clouds": 100, 
                "temp": 81.23, 
                "humidity": 81, 
                "pressure_sea": 1012.64, 
                "time": 1566842400, 
                "pressure_ground": 1011.81, 
                "time_str": "2019-08-26 18:00:00"
            }, 
            {
                "description": "light rain", 
                "rain": 2.25, 
                "wind_dir": 201.819, 
                "wind_speed": 3.54, 
                "clouds": 100, 
                "temp": 81.45, 
                "humidity": 84, 
                "pressure_sea": 1011.43, 
                "time": 1566853200, 
                "pressure_ground": 1010.54, 
                "time_str": "2019-08-26 21:00:00"
            }
        ], 
        "zip_code": "70119"
    }, 
    {
        "forecast": [
            {
                "description": "scattered clouds", 
                "rain": 0, 
                "wind_dir": 90.168, 
                "wind_speed": 3.75, 
                "clouds": 33, 
                "temp": 68.61, 
                "humidity": 57, 
                "pressure_sea": 1023.3, 
                "time": 1566777600, 
                "pressure_ground": 1015.18, 
                "time_str": "2019-08-26 00:00:00"
            }, 
            {
                "description": "few clouds", 
                "rain": 0, 
                "wind_dir": 61.07, 
                "wind_speed": 4.35, 
                "clouds": 16, 
                "temp": 66.2, 
                "humidity": 55, 
                "pressure_sea": 1023.82, 
                "time": 1566788400, 
                "pressure_ground": 1015.6, 
                "time_str": "2019-08-26 03:00:00"
            }, 
            {
                "description": "clear sky", 
                "rain": 0, 
                "wind_dir": 37.682, 
                "wind_speed": 3.95, 
                "clouds": 8, 
                "temp": 61.12, 
                "humidity": 58, 
                "pressure_sea": 1023.9, 
                "time": 1566799200, 
                "pressure_ground": 1015.63, 
                "time_str": "2019-08-26 06:00:00"
            }, 
            {
                "description": "few clouds", 
                "rain": 0, 
                "wind_dir": 31.953, 
                "wind_speed": 4.07, 
                "clouds": 12, 
                "temp": 57.76, 
                "humidity": 70, 
                "pressure_sea": 1023.5, 
                "time": 1566810000, 
                "pressure_ground": 1015.02, 
                "time_str": "2019-08-26 09:00:00"
            }, 
            {
                "description": "clear sky", 
                "rain": 0, 
                "wind_dir": 34.367, 
                "wind_speed": 3.71, 
                "clouds": 10, 
                "temp": 58.01, 
                "humidity": 69, 
                "pressure_sea": 1023.75, 
                "time": 1566820800, 
                "pressure_ground": 1015.52, 
                "time_str": "2019-08-26 12:00:00"
            }, 
            {
                "description": "clear sky", 
                "rain": 0, 
                "wind_dir": 66.976, 
                "wind_speed": 3.28, 
                "clouds": 0, 
                "temp": 68.83, 
                "humidity": 43, 
                "pressure_sea": 1023.29, 
                "time": 1566831600, 
                "pressure_ground": 1015.22, 
                "time_str": "2019-08-26 15:00:00"
            }, 
            {
                "description": "clear sky", 
                "rain": 0, 
                "wind_dir": 104.24, 
                "wind_speed": 4.1, 
                "clouds": 0, 
                "temp": 75.11, 
                "humidity": 33, 
                "pressure_sea": 1021.95, 
                "time": 1566842400, 
                "pressure_ground": 1013.78, 
                "time_str": "2019-08-26 18:00:00"
            }, 
            {
                "description": "clear sky", 
                "rain": 0, 
                "wind_dir": 106.569, 
                "wind_speed": 3.04, 
                "clouds": 0, 
                "temp": 75.69, 
                "humidity": 30, 
                "pressure_sea": 1020.02, 
                "time": 1566853200, 
                "pressure_ground": 1012.04, 
                "time_str": "2019-08-26 21:00:00"
            }
        ], 
        "zip_code": "11217"
    }
]