[
    {
        "forecast": [
            {
                "description": "broken clouds", 
                "rain": 0, 
                "wind_dir": 265.446, 
                "wind_speed": 4.64, 
                "clouds": 69, 
                "temp": 63.72, 
                "humidity": 62, 
                "pressure_sea": 1014.097, 
                "time": 1555459200, 
                "pressure_ground": 1000.458, 
                "time_str": "2019-04-17 00:00:00"
            }, 
            {
                "description": "clear sky", 
                "rain": 0, 
                "wind_dir": 257.845, 
                "wind_speed": 2.45, 
                "clouds": 1, 
                "temp": 60.73, 
                "humidity": 69, 
                "pressure_sea": 1015.814, 
                "time": 1555470000, 
                "pressure_ground": 1001.622, 
                "time_str": "2019-04-17 03:00:00"
            }, 
            {
                "description": "clear sky", 
                "rain": 0, 
                "wind_dir": 297.474, 
                "wind_speed": 0.37, 
                "clouds": 0, 
                "temp": 60.46, 
                "humidity": 70, 
                "pressure_sea": 1018.281, 
                "time": 1555480800, 
                "pressure_ground": 1003.972, 
                "time_str": "2019-04-17 06:00:00"
            }, 
            {
                "description": "clear sky", 
                "rain": 0, 
                "wind_dir": 102.001, 
                "wind_speed": 1.11, 
                "clouds": 0, 
                "temp": 59.47, 
                "humidity": 69, 
                "pressure_sea": 1019.108, 
                "time": 1555491600, 
                "pressure_ground": 1004.829, 
                "time_str": "2019-04-17 09:00:00"
            }, 
            {
                "description": "clear sky", 
                "rain": 0, 
                "wind_dir": 135.176, 
                "wind_speed": 0.69, 
                "clouds": 0, 
                "temp": 57.65, 
                "humidity": 73, 
                "pressure_sea": 1019.474, 
                "time": 1555502400, 
                "pressure_ground": 1005.373, 
                "time_str": "2019-04-17 12:00:00"
            }, 
            {
                "description": "clear sky", 
                "rain": 0, 
                "wind_dir": 106.105, 
                "wind_speed": 1.04, 
                "clouds": 0, 
                "temp": 59.09, 
                "humidity": 68, 
                "pressure_sea": 1020.385, 
                "time": 1555513200, 
                "pressure_ground": 1006.667, 
                "time_str": "2019-04-17 15:00:00"
            }, 
            {
                "description": "clear sky", 
                "rain": 0, 
                "wind_dir": 200.848, 
                "wind_speed": 1.91, 
                "clouds": 0, 
                "temp": 67.73, 
                "humidity": 49, 
                "pressure_sea": 1020.722, 
                "time": 1555524000, 
                "pressure_ground": 1007.069, 
                "time_str": "2019-04-17 18:00:00"
            }, 
            {
                "description": "clear sky", 
                "rain": 0, 
                "wind_dir": 229.732, 
                "wind_speed": 4.3, 
                "clouds": 0, 
                "temp": 72.8, 
                "humidity": 42, 
                "pressure_sea": 1019.418, 
                "time": 1555534800, 
                "pressure_ground": 1005.385, 
                "time_str": "2019-04-17 21:00:00"
            }
        ], 
        "zip_code": "90042"
    }, 
    {
        "forecast": [
            {
                "description": "scattered clouds", 
                "rain": 0, 
                "wind_dir": 142.118, 
                "wind_speed": 2.9, 
                "clouds": 49, 
                "temp": 67.32, 
                "humidity": 62, 
                "pressure_sea": 1018.971, 
                "time": 1555459200, 
                "pressure_ground": 1018.33, 
                "time_str": "2019-04-17 00:00:00"
            }, 
            {
                "description": "overcast clouds", 
                "rain": 0, 
                "wind_dir": 132.127, 
                "wind_speed": 3.02, 
                "clouds": 95, 
                "temp": 60.06, 
                "humidity": 78, 
                "pressure_sea": 1019.442, 
                "time": 1555470000, 
                "pressure_ground": 1019.046, 
                "time_str": "2019-04-17 03:00:00"
            }, 
            {
                "description": "overcast clouds", 
                "rain": 0, 
                "wind_dir": 135.085, 
                "wind_speed": 2.85, 
                "clouds": 97, 
                "temp": 60.03, 
                "humidity": 84, 
                "pressure_sea": 1019.037, 
                "time": 1555480800, 
                "pressure_ground": 1018.724, 
                "time_str": "2019-04-17 06:00:00"
            }, 
            {
                "description": "overcast clouds", 
                "rain": 0, 
                "wind_dir": 131.744, 
                "wind_speed": 2.76, 
                "clouds": 100, 
                "temp": 60.33, 
                "humidity": 91, 
                "pressure_sea": 1017.048, 
                "time": 1555491600, 
                "pressure_ground": 1016.797, 
                "time_str": "2019-04-17 09:00:00"
            }, 
            {
                "description": "overcast clouds", 
                "rain": 0, 
                "wind_dir": 131.221, 
                "wind_speed": 3.08, 
                "clouds": 100, 
                "temp": 62.33, 
                "humidity": 93, 
                "pressure_sea": 1016.3, 
                "time": 1555502400, 
                "pressure_ground": 1016.045, 
                "time_str": "2019-04-17 12:00:00"
            }, 
            {
                "description": "overcast clouds", 
                "rain": 0, 
                "wind_dir": 152.786, 
                "wind_speed": 3.99, 
                "clouds": 100, 
                "temp": 74.39, 
                "humidity": 67, 
                "pressure_sea": 1017.697, 
                "time": 1555513200, 
                "pressure_ground": 1017.387, 
                "time_str": "2019-04-17 15:00:00"
            }, 
            {
                "description": "overcast clouds", 
                "rain": 0, 
                "wind_dir": 157.298, 
                "wind_speed": 4.12, 
                "clouds": 100, 
                "temp": 81.95, 
                "humidity": 52, 
                "pressure_sea": 1017.182, 
                "time": 1555524000, 
                "pressure_ground": 1016.493, 
                "time_str": "2019-04-17 18:00:00"
            }, 
            {
                "description": "overcast clouds", 
                "rain": 0, 
                "wind_dir": 162.292, 
                "wind_speed": 4.91, 
                "clouds": 100, 
                "temp": 81.62, 
                "humidity": 50, 
                "pressure_sea": 1014.242, 
                "time": 1555534800, 
                "pressure_ground": 1013.609, 
                "time_str": "2019-04-17 21:00:00"
            }
        ], 
        "zip_code": "70119"
    }, 
    {
        "forecast": [
            {
                "description": "broken clouds", 
                "rain": 0, 
                "wind_dir": 318.531, 
                "wind_speed": 2.78, 
                "clouds": 66, 
                "temp": 53.4, 
                "humidity": 63, 
                "pressure_sea": 1016.915, 
                "time": 1555459200, 
                "pressure_ground": 986.442, 
                "time_str": "2019-04-17 00:00:00"
            }, 
            {
                "description": "light rain", 
                "rain": 1, 
                "wind_dir": 345.202, 
                "wind_speed": 1.81, 
                "clouds": 100, 
                "temp": 48.02, 
                "humidity": 82, 
                "pressure_sea": 1017.458, 
                "time": 1555470000, 
                "pressure_ground": 987.206, 
                "time_str": "2019-04-17 03:00:00"
            }, 
            {
                "description": "moderate rain", 
                "rain": 3.812, 
                "wind_dir": 33.668, 
                "wind_speed": 2.14, 
                "clouds": 100, 
                "temp": 45.09, 
                "humidity": 91, 
                "pressure_sea": 1018.019, 
                "time": 1555480800, 
                "pressure_ground": 987.252, 
                "time_str": "2019-04-17 06:00:00"
            }, 
            {
                "description": "light rain", 
                "rain": 0.688, 
                "wind_dir": 50.015, 
                "wind_speed": 1.63, 
                "clouds": 100, 
                "temp": 43.77, 
                "humidity": 89, 
                "pressure_sea": 1018.638, 
                "time": 1555491600, 
                "pressure_ground": 987.533, 
                "time_str": "2019-04-17 09:00:00"
            }, 
            {
                "description": "broken clouds", 
                "rain": 0, 
                "wind_dir": 50.42, 
                "wind_speed": 1.76, 
                "clouds": 66, 
                "temp": 43.79, 
                "humidity": 81, 
                "pressure_sea": 1020.572, 
                "time": 1555502400, 
                "pressure_ground": 989.645, 
                "time_str": "2019-04-17 12:00:00"
            }, 
            {
                "description": "clear sky", 
                "rain": 0, 
                "wind_dir": 40.27, 
                "wind_speed": 1.88, 
                "clouds": 3, 
                "temp": 53.51, 
                "humidity": 54, 
                "pressure_sea": 1021.511, 
                "time": 1555513200, 
                "pressure_ground": 990.571, 
                "time_str": "2019-04-17 15:00:00"
            }, 
            {
                "description": "few clouds", 
                "rain": 0, 
                "wind_dir": 49.683, 
                "wind_speed": 1.25, 
                "clouds": 16, 
                "temp": 63.05, 
                "humidity": 36, 
                "pressure_sea": 1020.584, 
                "time": 1555524000, 
                "pressure_ground": 990.045, 
                "time_str": "2019-04-17 18:00:00"
            }, 
            {
                "description": "clear sky", 
                "rain": 0, 
                "wind_dir": 96.084, 
                "wind_speed": 0.72, 
                "clouds": 0, 
                "temp": 63.08, 
                "humidity": 37, 
                "pressure_sea": 1019.598, 
                "time": 1555534800, 
                "pressure_ground": 989.209, 
                "time_str": "2019-04-17 21:00:00"
            }
        ], 
        "zip_code": "11217"
    }
]