[
    {
        "forecast": [
            {
                "description": "clear sky", 
                "rain": 0, 
                "wind_dir": 218.436, 
                "wind_speed": 3.07, 
                "clouds": 6, 
                "temp": 72.39, 
                "humidity": 60, 
                "pressure_sea": 1010.91, 
                "time": 1559952000, 
                "pressure_ground": 997.73, 
                "time_str": "2019-06-08 00:00:00"
            }, 
            {
                "description": "clear sky", 
                "rain": 0, 
                "wind_dir": 201.828, 
                "wind_speed": 2, 
                "clouds": 0, 
                "temp": 68.63, 
                "humidity": 65, 
                "pressure_sea": 1011.38, 
                "time": 1559962800, 
                "pressure_ground": 997.53, 
                "time_str": "2019-06-08 03:00:00"
            }, 
            {
                "description": "clear sky", 
                "rain": 0, 
                "wind_dir": 157.533, 
                "wind_speed": 1.87, 
                "clouds": 0, 
                "temp": 66.38, 
                "humidity": 69, 
                "pressure_sea": 1011.96, 
                "time": 1559973600, 
                "pressure_ground": 997.99, 
                "time_str": "2019-06-08 06:00:00"
            }, 
            {
                "description": "clear sky", 
                "rain": 0, 
                "wind_dir": 137.36, 
                "wind_speed": 2.23, 
                "clouds": 0, 
                "temp": 64.53, 
                "humidity": 70, 
                "pressure_sea": 1011.63, 
                "time": 1559984400, 
                "pressure_ground": 997.76, 
                "time_str": "2019-06-08 09:00:00"
            }, 
            {
                "description": "clear sky", 
                "rain": 0, 
                "wind_dir": 127.985, 
                "wind_speed": 1.83, 
                "clouds": 0, 
                "temp": 63.24, 
                "humidity": 75, 
                "pressure_sea": 1011.89, 
                "time": 1559995200, 
                "pressure_ground": 998.08, 
                "time_str": "2019-06-08 12:00:00"
            }, 
            {
                "description": "clear sky", 
                "rain": 0, 
                "wind_dir": 135.233, 
                "wind_speed": 1.91, 
                "clouds": 0, 
                "temp": 66.07, 
                "humidity": 68, 
                "pressure_sea": 1012.71, 
                "time": 1560006000, 
                "pressure_ground": 999.06, 
                "time_str": "2019-06-08 15:00:00"
            }, 
            {
                "description": "clear sky", 
                "rain": 0, 
                "wind_dir": 180.465, 
                "wind_speed": 3.2, 
                "clouds": 0, 
                "temp": 73.04, 
                "humidity": 52, 
                "pressure_sea": 1013.07, 
                "time": 1560016800, 
                "pressure_ground": 999.43, 
                "time_str": "2019-06-08 18:00:00"
            }, 
            {
                "description": "clear sky", 
                "rain": 0, 
                "wind_dir": 205.826, 
                "wind_speed": 3.92, 
                "clouds": 0, 
                "temp": 76.61, 
                "humidity": 46, 
                "pressure_sea": 1012.45, 
                "time": 1560027600, 
                "pressure_ground": 998.99, 
                "time_str": "2019-06-08 21:00:00"
            }
        ], 
        "zip_code": "90042"
    }, 
    {
        "forecast": [
            {
                "description": "light rain", 
                "rain": 2.938, 
                "wind_dir": 251.446, 
                "wind_speed": 1.97, 
                "clouds": 3, 
                "temp": 83.37, 
                "humidity": 78, 
                "pressure_sea": 1005.59, 
                "time": 1559952000, 
                "pressure_ground": 1004.97, 
                "time_str": "2019-06-08 00:00:00"
            }, 
            {
                "description": "light rain", 
                "rain": 0.562, 
                "wind_dir": 232.619, 
                "wind_speed": 2.8, 
                "clouds": 9, 
                "temp": 75.38, 
                "humidity": 90, 
                "pressure_sea": 1006.94, 
                "time": 1559962800, 
                "pressure_ground": 1006.62, 
                "time_str": "2019-06-08 03:00:00"
            }, 
            {
                "description": "light rain", 
                "rain": 1.126, 
                "wind_dir": 213.723, 
                "wind_speed": 3.34, 
                "clouds": 4, 
                "temp": 74.84, 
                "humidity": 94, 
                "pressure_sea": 1007, 
                "time": 1559973600, 
                "pressure_ground": 1006.42, 
                "time_str": "2019-06-08 06:00:00"
            }, 
            {
                "description": "light rain", 
                "rain": 0.062, 
                "wind_dir": 224.016, 
                "wind_speed": 3.05, 
                "clouds": 1, 
                "temp": 74.52, 
                "humidity": 94, 
                "pressure_sea": 1006.05, 
                "time": 1559984400, 
                "pressure_ground": 1005.54, 
                "time_str": "2019-06-08 09:00:00"
            }, 
            {
                "description": "light rain", 
                "rain": 0.626, 
                "wind_dir": 216.633, 
                "wind_speed": 3.2, 
                "clouds": 2, 
                "temp": 75.84, 
                "humidity": 91, 
                "pressure_sea": 1006.92, 
                "time": 1559995200, 
                "pressure_ground": 1006.19, 
                "time_str": "2019-06-08 12:00:00"
            }, 
            {
                "description": "moderate rain", 
                "rain": 3.625, 
                "wind_dir": 252.67, 
                "wind_speed": 4.05, 
                "clouds": 1, 
                "temp": 82.99, 
                "humidity": 77, 
                "pressure_sea": 1007.53, 
                "time": 1560006000, 
                "pressure_ground": 1007.14, 
                "time_str": "2019-06-08 15:00:00"
            }, 
            {
                "description": "light rain", 
                "rain": 0.25, 
                "wind_dir": 265.397, 
                "wind_speed": 3.79, 
                "clouds": 2, 
                "temp": 90.86, 
                "humidity": 52, 
                "pressure_sea": 1007.33, 
                "time": 1560016800, 
                "pressure_ground": 1006.74, 
                "time_str": "2019-06-08 18:00:00"
            }, 
            {
                "description": "clear sky", 
                "rain": 0, 
                "wind_dir": 276.839, 
                "wind_speed": 4.06, 
                "clouds": 7, 
                "temp": 92.09, 
                "humidity": 48, 
                "pressure_sea": 1006.22, 
                "time": 1560027600, 
                "pressure_ground": 1005.49, 
                "time_str": "2019-06-08 21:00:00"
            }
        ], 
        "zip_code": "70119"
    }, 
    {
        "forecast": [
            {
                "description": "overcast clouds", 
                "rain": 0, 
                "wind_dir": 176.512, 
                "wind_speed": 0.97, 
                "clouds": 100, 
                "temp": 68.2, 
                "humidity": 66, 
                "pressure_sea": 1014.12, 
                "time": 1559952000, 
                "pressure_ground": 984.14, 
                "time_str": "2019-06-08 00:00:00"
            }, 
            {
                "description": "overcast clouds", 
                "rain": 0, 
                "wind_dir": 301.855, 
                "wind_speed": 0.61, 
                "clouds": 100, 
                "temp": 62.94, 
                "humidity": 76, 
                "pressure_sea": 1016.18, 
                "time": 1559962800, 
                "pressure_ground": 986.24, 
                "time_str": "2019-06-08 03:00:00"
            }, 
            {
                "description": "overcast clouds", 
                "rain": 0, 
                "wind_dir": 20.709, 
                "wind_speed": 1.63, 
                "clouds": 100, 
                "temp": 60.6, 
                "humidity": 85, 
                "pressure_sea": 1017.01, 
                "time": 1559973600, 
                "pressure_ground": 987.13, 
                "time_str": "2019-06-08 06:00:00"
            }, 
            {
                "description": "overcast clouds", 
                "rain": 0, 
                "wind_dir": 12.786, 
                "wind_speed": 2.22, 
                "clouds": 100, 
                "temp": 58.12, 
                "humidity": 84, 
                "pressure_sea": 1018.09, 
                "time": 1559984400, 
                "pressure_ground": 988.19, 
                "time_str": "2019-06-08 09:00:00"
            }, 
            {
                "description": "overcast clouds", 
                "rain": 0, 
                "wind_dir": 35.49, 
                "wind_speed": 3.6, 
                "clouds": 100, 
                "temp": 63.42, 
                "humidity": 66, 
                "pressure_sea": 1019.66, 
                "time": 1559995200, 
                "pressure_ground": 990.09, 
                "time_str": "2019-06-08 12:00:00"
            }, 
            {
                "description": "overcast clouds", 
                "rain": 0, 
                "wind_dir": 50.568, 
                "wind_speed": 3.94, 
                "clouds": 100, 
                "temp": 73.81, 
                "humidity": 44, 
                "pressure_sea": 1020.66, 
                "time": 1560006000, 
                "pressure_ground": 991.05, 
                "time_str": "2019-06-08 15:00:00"
            }, 
            {
                "description": "overcast clouds", 
                "rain": 0, 
                "wind_dir": 55.594, 
                "wind_speed": 3.11, 
                "clouds": 100, 
                "temp": 79.52, 
                "humidity": 35, 
                "pressure_sea": 1020.78, 
                "time": 1560016800, 
                "pressure_ground": 990.93, 
                "time_str": "2019-06-08 18:00:00"
            }, 
            {
                "description": "overcast clouds", 
                "rain": 0, 
                "wind_dir": 92.262, 
                "wind_speed": 2.21, 
                "clouds": 100, 
                "temp": 79.85, 
                "humidity": 36, 
                "pressure_sea": 1020.46, 
                "time": 1560027600, 
                "pressure_ground": 990.42, 
                "time_str": "2019-06-08 21:00:00"
            }
        ], 
        "zip_code": "11217"
    }
]